<?xml version="1.0"?>
<npl:medprod xmlns:xsi="http://www.w3.org/2001/XMLSchema-instance" xmlns:mpa="urn:schemas-npl:mpa:12" xsi:schemaLocation="urn:schemas-npl:instance:12 ../schemas/npl-schema_12.0.xsd" xmlns:npl="urn:schemas-npl:instance:12">
  <mpa:nplid>20101231000075</mpa:nplid>
  <npl:approvalnumber>
    <mpa:semano>456460</mpa:semano>
    <mpa:nat-ma-no>45646</mpa:nat-ma-no>
  </npl:approvalnumber>
  <npl:names>
    <mpa:medprodname v="Kudeq®" />
    <mpa:medprodnamelegal v="Kudeq" />
    <mpa:historicalmedprodname v="Kudeq" vtodate="2014-02-06" />
    <mpa:historicalmedprodnamelegal v="Kudeq" vtodate="2014-02-06" />
  </npl:names>
  <mpa:strength-text>
    <mpa:v>100 mg</mpa:v>
  </mpa:strength-text>
  <mpa:pharmaceutical-form-lx v="CAPHAR" lexicon="pharmaceutical-form-lx" />
  <npl:organizations>
    <mpa:organization>
      <mpa:organization-lx v="IDYT419510ZJW8KMSR" />
      <mpa:organization-role-lx v="MAH" lexicon="organization-role-lx" />
    </mpa:organization>
  </npl:organizations>
  <mpa:approvaldate>2012-05-04</mpa:approvaldate>
  <mpa:withdrawaldate>2015-06-30</mpa:withdrawaldate>
  <mpa:productclass-lx v="MEP" lexicon="productclass-lx" />
  <mpa:prescription-lx v="1" lexicon="prescription-lx" />
  <npl:classifications>
    <mpa:atc-code-lx v="M01AH01" />
    <mpa:controlled-medicinal-product-lx v="N" lexicon="yesno-lx" />
    <mpa:narcotic-class-lx v="0" lexicon="narcotic-classification-lx" />
  </npl:classifications>
  <mpa:authorisation-procedure-lx v="4" lexicon="authorisation-procedure-lx" />
  <npl:flags>
    <mpa:salesstopped v="N" lexicon="yesno-lx" />
    <mpa:biological-medprod-pharmaceutical-legislation v="N" lexicon="yesno-lx" />
    <mpa:antimicrobial v="N" lexicon="yesno-lx" />
  </npl:flags>
  <npl:pharmaceutical-products>
    <npl:pharmaceutical-product id="IDMNT98Z7ZGQ6JSRV0">
      <npl:composition>
        <npl:ingredient id="IDF7OISRV0HD8NSRV0">
          <mpa:ingredient-role-lx v="MISC" lexicon="ingredient-role-lx" />
          <mpa:substance-lx v="IDE4POBUU91KVVERT1" />
        </npl:ingredient>
        <npl:ingredient id="IDMNT98Z7ZGQAGSRV0">
          <mpa:ingredient-role-lx v="MISC" lexicon="ingredient-role-lx" />
          <mpa:substance-lx v="IDE4POC7U9C0ZVERT1" />
        </npl:ingredient>
        <npl:ingredient id="IDMNT98Z7ZGQLASRV0">
          <mpa:ingredient-role-lx v="MISC" lexicon="ingredient-role-lx" />
          <mpa:substance-lx v="IDE4POI8UC9O7VERT1" />
        </npl:ingredient>
        <npl:ingredient id="IDMNT98Z7ZGQNHSRV0">
          <mpa:ingredient-role-lx v="ACTI" lexicon="ingredient-role-lx" />
          <mpa:quantity v="100" />
          <mpa:quantity-unit-lx v="03" lexicon="quantity-unit-lx" />
          <mpa:quantity-unit-alt-lx v="EQ" lexicon="quantity-unit-alt-lx" />
          <mpa:substance-lx v="IDE4POIDUCD54VERT1" />
        </npl:ingredient>
      </npl:composition>
      <mpa:comp-ref-quantity-lx v="FGE" lexicon="comp-ref-quantity-lx" />
    </npl:pharmaceutical-product>
  </npl:pharmaceutical-products>
  <npl:packages>
    <npl:package>
      <mpa:nplpackid>20120426100307</mpa:nplpackid>
      <mpa:pack-text>
        <mpa:v>Blister, 10 kapslar</mpa:v>
      </mpa:pack-text>
      <mpa:pack-withdrawaldate>2015-06-30</mpa:pack-withdrawaldate>
      <npl:prescription>
        <mpa:otc v="N" lexicon="yesno-lx" />
      </npl:prescription>
      <npl:prescribers>
        <mpa:prescriber-lx v="2" lexicon="prescriber-lx" />
      </npl:prescribers>
      <npl:storage>
        <mpa:pack-condition-lx v="1" lexicon="pack-condition-lx" id="ID1AAMQ7WIZ0TAVSRV" pharmaceutical-product-id="IDMNT98Z7ZGQ6JSRV0">
          <mpa:shelf-life v="3">
            <mpa:shelf-life-unit-lx v="5" lexicon="shelf-life-unit-lx" />
            <mpa:storage-temp-lx v="2" lexicon="storage-temp-lx" />
          </mpa:shelf-life>
        </mpa:pack-condition-lx>
      </npl:storage>
    </npl:package>
    <npl:package>
      <mpa:nplpackid>20120426100192</mpa:nplpackid>
      <mpa:pack-text>
        <mpa:v>Blister, 100 (10x10) kapslar</mpa:v>
      </mpa:pack-text>
      <mpa:pack-withdrawaldate>2015-06-30</mpa:pack-withdrawaldate>
      <npl:prescription>
        <mpa:otc v="N" lexicon="yesno-lx" />
      </npl:prescription>
      <npl:prescribers>
        <mpa:prescriber-lx v="2" lexicon="prescriber-lx" />
      </npl:prescribers>
      <npl:storage>
        <mpa:pack-condition-lx v="1" lexicon="pack-condition-lx" id="ID1AAMQ7XIZ0ULQSRV" pharmaceutical-product-id="IDMNT98Z7ZGQ6JSRV0">
          <mpa:shelf-life v="3">
            <mpa:shelf-life-unit-lx v="5" lexicon="shelf-life-unit-lx" />
            <mpa:storage-temp-lx v="2" lexicon="storage-temp-lx" />
          </mpa:shelf-life>
        </mpa:pack-condition-lx>
      </npl:storage>
    </npl:package>
    <npl:package>
      <mpa:nplpackid>20120426100260</mpa:nplpackid>
      <mpa:pack-text>
        <mpa:v>Blister, 100 kapslar</mpa:v>
      </mpa:pack-text>
      <mpa:pack-withdrawaldate>2015-06-30</mpa:pack-withdrawaldate>
      <npl:prescription>
        <mpa:otc v="N" lexicon="yesno-lx" />
      </npl:prescription>
      <npl:prescribers>
        <mpa:prescriber-lx v="2" lexicon="prescriber-lx" />
      </npl:prescribers>
      <npl:storage>
        <mpa:pack-condition-lx v="1" lexicon="pack-condition-lx" id="ID1AAMQ7XIZ0UESSRV" pharmaceutical-product-id="IDMNT98Z7ZGQ6JSRV0">
          <mpa:shelf-life v="3">
            <mpa:shelf-life-unit-lx v="5" lexicon="shelf-life-unit-lx" />
            <mpa:storage-temp-lx v="2" lexicon="storage-temp-lx" />
          </mpa:shelf-life>
        </mpa:pack-condition-lx>
      </npl:storage>
    </npl:package>
    <npl:package>
      <mpa:nplpackid>20120426100291</mpa:nplpackid>
      <mpa:pack-text>
        <mpa:v>Blister, 100 x 1 tabletter (endos)</mpa:v>
      </mpa:pack-text>
      <mpa:pack-withdrawaldate>2015-06-30</mpa:pack-withdrawaldate>
      <npl:prescription>
        <mpa:otc v="N" lexicon="yesno-lx" />
      </npl:prescription>
      <npl:prescribers>
        <mpa:prescriber-lx v="2" lexicon="prescriber-lx" />
      </npl:prescribers>
      <npl:storage>
        <mpa:pack-condition-lx v="1" lexicon="pack-condition-lx" id="ID1AAMQO6IZ8893SRV" pharmaceutical-product-id="IDMNT98Z7ZGQ6JSRV0">
          <mpa:shelf-life v="3">
            <mpa:shelf-life-unit-lx v="5" lexicon="shelf-life-unit-lx" />
            <mpa:storage-temp-lx v="2" lexicon="storage-temp-lx" />
          </mpa:shelf-life>
        </mpa:pack-condition-lx>
      </npl:storage>
    </npl:package>
    <npl:package>
      <mpa:nplpackid>20120426100208</mpa:nplpackid>
      <mpa:pack-text>
        <mpa:v>Blister, 2 kapslar</mpa:v>
      </mpa:pack-text>
      <mpa:pack-withdrawaldate>2015-06-30</mpa:pack-withdrawaldate>
      <npl:prescription>
        <mpa:otc v="N" lexicon="yesno-lx" />
      </npl:prescription>
      <npl:prescribers>
        <mpa:prescriber-lx v="2" lexicon="prescriber-lx" />
      </npl:prescribers>
      <npl:storage>
        <mpa:pack-condition-lx v="1" lexicon="pack-condition-lx" id="ID1AAMQ7VIZ0SQWSRV" pharmaceutical-product-id="IDMNT98Z7ZGQ6JSRV0">
          <mpa:shelf-life v="3">
            <mpa:shelf-life-unit-lx v="5" lexicon="shelf-life-unit-lx" />
            <mpa:storage-temp-lx v="2" lexicon="storage-temp-lx" />
          </mpa:shelf-life>
        </mpa:pack-condition-lx>
      </npl:storage>
    </npl:package>
    <npl:package>
      <mpa:nplpackid>20120426100338</mpa:nplpackid>
      <mpa:pack-text>
        <mpa:v>Blister, 20 kapslar</mpa:v>
      </mpa:pack-text>
      <mpa:pack-withdrawaldate>2015-06-30</mpa:pack-withdrawaldate>
      <npl:prescription>
        <mpa:otc v="N" lexicon="yesno-lx" />
      </npl:prescription>
      <npl:prescribers>
        <mpa:prescriber-lx v="2" lexicon="prescriber-lx" />
      </npl:prescribers>
      <npl:storage>
        <mpa:pack-condition-lx v="1" lexicon="pack-condition-lx" id="ID1AAMQ7WIZ0THDSRV" pharmaceutical-product-id="IDMNT98Z7ZGQ6JSRV0">
          <mpa:shelf-life v="3">
            <mpa:shelf-life-unit-lx v="5" lexicon="shelf-life-unit-lx" />
            <mpa:storage-temp-lx v="2" lexicon="storage-temp-lx" />
          </mpa:shelf-life>
        </mpa:pack-condition-lx>
      </npl:storage>
    </npl:package>
    <npl:package>
      <mpa:nplpackid>20120426100314</mpa:nplpackid>
      <mpa:pack-text>
        <mpa:v>Blister, 30 kapslar</mpa:v>
      </mpa:pack-text>
      <mpa:pack-withdrawaldate>2015-06-30</mpa:pack-withdrawaldate>
      <npl:prescription>
        <mpa:otc v="N" lexicon="yesno-lx" />
      </npl:prescription>
      <npl:prescribers>
        <mpa:prescriber-lx v="2" lexicon="prescriber-lx" />
      </npl:prescribers>
      <npl:storage>
        <mpa:pack-condition-lx v="1" lexicon="pack-condition-lx" id="ID1AAMQ7WIZ0TNVSRV" pharmaceutical-product-id="IDMNT98Z7ZGQ6JSRV0">
          <mpa:shelf-life v="3">
            <mpa:shelf-life-unit-lx v="5" lexicon="shelf-life-unit-lx" />
            <mpa:storage-temp-lx v="2" lexicon="storage-temp-lx" />
          </mpa:shelf-life>
        </mpa:pack-condition-lx>
      </npl:storage>
    </npl:package>
    <npl:package>
      <mpa:nplpackid>20120426100185</mpa:nplpackid>
      <mpa:pack-text>
        <mpa:v>Blister, 300 (10x30) kapslar</mpa:v>
      </mpa:pack-text>
      <mpa:pack-withdrawaldate>2015-06-30</mpa:pack-withdrawaldate>
      <npl:prescription>
        <mpa:otc v="N" lexicon="yesno-lx" />
      </npl:prescription>
      <npl:prescribers>
        <mpa:prescriber-lx v="2" lexicon="prescriber-lx" />
      </npl:prescribers>
      <npl:storage>
        <mpa:pack-condition-lx v="1" lexicon="pack-condition-lx" id="ID1AAMQ7VIZ0SDGSRV" pharmaceutical-product-id="IDMNT98Z7ZGQ6JSRV0">
          <mpa:shelf-life v="3">
            <mpa:shelf-life-unit-lx v="5" lexicon="shelf-life-unit-lx" />
            <mpa:storage-temp-lx v="2" lexicon="storage-temp-lx" />
          </mpa:shelf-life>
        </mpa:pack-condition-lx>
      </npl:storage>
    </npl:package>
    <npl:package>
      <mpa:nplpackid>20120426100215</mpa:nplpackid>
      <mpa:pack-text>
        <mpa:v>Blister, 40 kapslar</mpa:v>
      </mpa:pack-text>
      <mpa:pack-withdrawaldate>2015-06-30</mpa:pack-withdrawaldate>
      <npl:prescription>
        <mpa:otc v="N" lexicon="yesno-lx" />
      </npl:prescription>
      <npl:prescribers>
        <mpa:prescriber-lx v="2" lexicon="prescriber-lx" />
      </npl:prescribers>
      <npl:storage>
        <mpa:pack-condition-lx v="1" lexicon="pack-condition-lx" id="ID1AAMQ7WIZ0TUESRV" pharmaceutical-product-id="IDMNT98Z7ZGQ6JSRV0">
          <mpa:shelf-life v="3">
            <mpa:shelf-life-unit-lx v="5" lexicon="shelf-life-unit-lx" />
            <mpa:storage-temp-lx v="2" lexicon="storage-temp-lx" />
          </mpa:shelf-life>
        </mpa:pack-condition-lx>
      </npl:storage>
    </npl:package>
    <npl:package>
      <mpa:nplpackid>20120426100239</mpa:nplpackid>
      <mpa:pack-text>
        <mpa:v>Blister, 5 kapslar</mpa:v>
      </mpa:pack-text>
      <mpa:pack-withdrawaldate>2015-06-30</mpa:pack-withdrawaldate>
      <npl:prescription>
        <mpa:otc v="N" lexicon="yesno-lx" />
      </npl:prescription>
      <npl:prescribers>
        <mpa:prescriber-lx v="2" lexicon="prescriber-lx" />
      </npl:prescribers>
      <npl:storage>
        <mpa:pack-condition-lx v="1" lexicon="pack-condition-lx" id="ID1AAMQ7VIZ0SXESRV" pharmaceutical-product-id="IDMNT98Z7ZGQ6JSRV0">
          <mpa:shelf-life v="3">
            <mpa:shelf-life-unit-lx v="5" lexicon="shelf-life-unit-lx" />
            <mpa:storage-temp-lx v="2" lexicon="storage-temp-lx" />
          </mpa:shelf-life>
        </mpa:pack-condition-lx>
      </npl:storage>
    </npl:package>
    <npl:package>
      <mpa:nplpackid>20120426100284</mpa:nplpackid>
      <mpa:pack-text>
        <mpa:v>Blister, 50 kapslar</mpa:v>
      </mpa:pack-text>
      <mpa:pack-withdrawaldate>2015-06-30</mpa:pack-withdrawaldate>
      <npl:prescription>
        <mpa:otc v="N" lexicon="yesno-lx" />
      </npl:prescription>
      <npl:prescribers>
        <mpa:prescriber-lx v="2" lexicon="prescriber-lx" />
      </npl:prescribers>
      <npl:storage>
        <mpa:pack-condition-lx v="1" lexicon="pack-condition-lx" id="ID1AAMQ7XIZ0U0WSRV" pharmaceutical-product-id="IDMNT98Z7ZGQ6JSRV0">
          <mpa:shelf-life v="3">
            <mpa:shelf-life-unit-lx v="5" lexicon="shelf-life-unit-lx" />
            <mpa:storage-temp-lx v="2" lexicon="storage-temp-lx" />
          </mpa:shelf-life>
        </mpa:pack-condition-lx>
      </npl:storage>
    </npl:package>
    <npl:package>
      <mpa:nplpackid>20120426100253</mpa:nplpackid>
      <mpa:pack-text>
        <mpa:v>Blister, 50 x 1 tabletter (endos)</mpa:v>
      </mpa:pack-text>
      <mpa:pack-withdrawaldate>2015-06-30</mpa:pack-withdrawaldate>
      <npl:prescription>
        <mpa:otc v="N" lexicon="yesno-lx" />
      </npl:prescription>
      <npl:prescribers>
        <mpa:prescriber-lx v="2" lexicon="prescriber-lx" />
      </npl:prescribers>
      <npl:storage>
        <mpa:pack-condition-lx v="1" lexicon="pack-condition-lx" id="ID1AAMQMCIZ7O9XSRV" pharmaceutical-product-id="IDMNT98Z7ZGQ6JSRV0">
          <mpa:shelf-life v="3">
            <mpa:shelf-life-unit-lx v="5" lexicon="shelf-life-unit-lx" />
            <mpa:storage-temp-lx v="2" lexicon="storage-temp-lx" />
          </mpa:shelf-life>
        </mpa:pack-condition-lx>
      </npl:storage>
    </npl:package>
    <npl:package>
      <mpa:nplpackid>20120426100277</mpa:nplpackid>
      <mpa:pack-text>
        <mpa:v>Blister, 500 (10x50) kapslar</mpa:v>
      </mpa:pack-text>
      <mpa:pack-withdrawaldate>2015-06-30</mpa:pack-withdrawaldate>
      <npl:prescription>
        <mpa:otc v="N" lexicon="yesno-lx" />
      </npl:prescription>
      <npl:prescribers>
        <mpa:prescriber-lx v="2" lexicon="prescriber-lx" />
      </npl:prescribers>
      <npl:storage>
        <mpa:pack-condition-lx v="1" lexicon="pack-condition-lx" id="ID1AAMQ7VIZ0SJYSRV" pharmaceutical-product-id="IDMNT98Z7ZGQ6JSRV0">
          <mpa:shelf-life v="3">
            <mpa:shelf-life-unit-lx v="5" lexicon="shelf-life-unit-lx" />
            <mpa:storage-temp-lx v="2" lexicon="storage-temp-lx" />
          </mpa:shelf-life>
        </mpa:pack-condition-lx>
      </npl:storage>
    </npl:package>
    <npl:package>
      <mpa:nplpackid>20120426100246</mpa:nplpackid>
      <mpa:pack-text>
        <mpa:v>Blister, 500 (5x10x10) kapslar</mpa:v>
      </mpa:pack-text>
      <mpa:pack-withdrawaldate>2015-06-30</mpa:pack-withdrawaldate>
      <npl:prescription>
        <mpa:otc v="N" lexicon="yesno-lx" />
      </npl:prescription>
      <npl:prescribers>
        <mpa:prescriber-lx v="2" lexicon="prescriber-lx" />
      </npl:prescribers>
      <npl:storage>
        <mpa:pack-condition-lx v="1" lexicon="pack-condition-lx" id="ID1AAMQ73IZ0723SRV" pharmaceutical-product-id="IDMNT98Z7ZGQ6JSRV0">
          <mpa:shelf-life v="3">
            <mpa:shelf-life-unit-lx v="5" lexicon="shelf-life-unit-lx" />
            <mpa:storage-temp-lx v="2" lexicon="storage-temp-lx" />
          </mpa:shelf-life>
        </mpa:pack-condition-lx>
      </npl:storage>
    </npl:package>
    <npl:package>
      <mpa:nplpackid>20120426100222</mpa:nplpackid>
      <mpa:pack-text>
        <mpa:v>Blister, 6 kapslar</mpa:v>
      </mpa:pack-text>
      <mpa:pack-withdrawaldate>2015-06-30</mpa:pack-withdrawaldate>
      <npl:prescription>
        <mpa:otc v="N" lexicon="yesno-lx" />
      </npl:prescription>
      <npl:prescribers>
        <mpa:prescriber-lx v="2" lexicon="prescriber-lx" />
      </npl:prescribers>
      <npl:storage>
        <mpa:pack-condition-lx v="1" lexicon="pack-condition-lx" id="ID1AAMQ7WIZ0T3XSRV" pharmaceutical-product-id="IDMNT98Z7ZGQ6JSRV0">
          <mpa:shelf-life v="3">
            <mpa:shelf-life-unit-lx v="5" lexicon="shelf-life-unit-lx" />
            <mpa:storage-temp-lx v="2" lexicon="storage-temp-lx" />
          </mpa:shelf-life>
        </mpa:pack-condition-lx>
      </npl:storage>
    </npl:package>
    <npl:package>
      <mpa:nplpackid>20120426100321</mpa:nplpackid>
      <mpa:pack-text>
        <mpa:v>Blister, 60 kapslar</mpa:v>
      </mpa:pack-text>
      <mpa:pack-withdrawaldate>2015-06-30</mpa:pack-withdrawaldate>
      <npl:prescription>
        <mpa:otc v="N" lexicon="yesno-lx" />
      </npl:prescription>
      <npl:prescribers>
        <mpa:prescriber-lx v="2" lexicon="prescriber-lx" />
      </npl:prescribers>
      <npl:storage>
        <mpa:pack-condition-lx v="1" lexicon="pack-condition-lx" id="ID1AAMQ7XIZ0U7USRV" pharmaceutical-product-id="IDMNT98Z7ZGQ6JSRV0">
          <mpa:shelf-life v="3">
            <mpa:shelf-life-unit-lx v="5" lexicon="shelf-life-unit-lx" />
            <mpa:storage-temp-lx v="2" lexicon="storage-temp-lx" />
          </mpa:shelf-life>
        </mpa:pack-condition-lx>
      </npl:storage>
    </npl:package>
  </npl:packages>
</npl:medprod>
