<?xml version="1.0"?>
<npl:medprod xmlns:xsi="http://www.w3.org/2001/XMLSchema-instance" xmlns:mpa="urn:schemas-npl:mpa:12" xsi:schemaLocation="urn:schemas-npl:instance:12 ../schemas/npl-schema_12.0.xsd" xmlns:npl="urn:schemas-npl:instance:12">
  <mpa:nplid>20120824000063</mpa:nplid>
  <npl:approvalnumber>
    <mpa:semano>484810</mpa:semano>
    <mpa:nat-ma-no>48481</mpa:nat-ma-no>
  </npl:approvalnumber>
  <npl:names>
    <mpa:medprodname v="Targiniq" />
    <mpa:medprodnamelegal v="Targiniq" />
  </npl:names>
  <mpa:strength-text>
    <mpa:v>30 mg/15 mg</mpa:v>
  </mpa:strength-text>
  <mpa:pharmaceutical-form-lx v="PRRETA" lexicon="pharmaceutical-form-lx" />
  <npl:route-of-administrations>
    <mpa:route-of-administration-lx v="ORAL" lexicon="route-of-administration-lx" />
  </npl:route-of-administrations>
  <npl:organizations>
    <mpa:organization>
      <mpa:organization-lx v="IDX0000001428" />
      <mpa:organization-role-lx v="MAH" lexicon="organization-role-lx" />
    </mpa:organization>
  </npl:organizations>
  <mpa:approvaldate>2013-12-16</mpa:approvaldate>
  <mpa:withdrawaldate>2020-11-05</mpa:withdrawaldate>
  <mpa:productclass-lx v="MEP" lexicon="productclass-lx" />
  <mpa:prescription-lx v="1" lexicon="prescription-lx" />
  <npl:classifications>
    <mpa:atc-code-lx v="N02AA55" />
    <mpa:controlled-medicinal-product-lx v="Y" lexicon="yesno-lx" />
    <mpa:repeat-prescription-lx v="004" lexicon="repeat-prescription-lx" />
    <mpa:narcotic-class-lx v="1" lexicon="narcotic-classification-lx" />
  </npl:classifications>
  <mpa:authorisation-procedure-lx v="4" lexicon="authorisation-procedure-lx" />
  <npl:flags>
    <mpa:salesstopped v="N" lexicon="yesno-lx" />
    <mpa:dosdisp v="Y" lexicon="yesno-lx" />
    <mpa:biological-medprod-pharmaceutical-legislation v="N" lexicon="yesno-lx" />
    <mpa:antimicrobial v="N" lexicon="yesno-lx" />
  </npl:flags>
  <npl:pharmaceutical-products>
    <npl:pharmaceutical-product id="ID1GVKQ29A8KTOPSRV">
      <npl:composition>
        <npl:ingredient id="ID1GVKQ29A8KTRBSRV" substance-for-reference-strength="Y">
          <mpa:ingredient-role-lx v="ACTI" lexicon="ingredient-role-lx" />
          <mpa:quantity v="30" />
          <mpa:quantity-unit-lx v="03" lexicon="quantity-unit-lx" />
          <mpa:quantity-unit-alt-lx v="EQ" lexicon="quantity-unit-alt-lx" />
          <mpa:substance-lx v="IDE4POC4U99E4VERT1" />
        </npl:ingredient>
        <npl:ingredient id="ID1GVKQ2AA8KTSLSRV">
          <mpa:ingredient-role-lx v="ACTI" lexicon="ingredient-role-lx" />
          <mpa:quantity v="16.48" />
          <mpa:quantity-unit-lx v="03" lexicon="quantity-unit-lx" />
          <mpa:quantity-unit-alt-lx v="EQ" lexicon="quantity-unit-alt-lx" />
          <mpa:substance-lx v="ID1IRRTQK19WL3NHMS" />
        </npl:ingredient>
        <npl:ingredient id="ID1GVKQ2AA8KTTWSRV" related-to-id="ID1GVKQ29A8KTRBSRV" presentation-substance-name="Y">
          <mpa:ingredient-role-lx v="ARES" lexicon="ingredient-role-lx" />
          <mpa:quantity v="27" />
          <mpa:quantity-unit-lx v="03" lexicon="quantity-unit-lx" />
          <mpa:quantity-unit-alt-lx v="EQ" lexicon="quantity-unit-alt-lx" />
          <mpa:substance-lx v="IDE4POBYU94E4VERT1" />
        </npl:ingredient>
        <npl:ingredient id="ID1GVKQ2AA8KTV7SRV" related-to-id="ID1GVKQ2AA8KTSLSRV" substance-for-reference-strength="Y">
          <mpa:ingredient-role-lx v="ARES" lexicon="ingredient-role-lx" />
          <mpa:quantity v="15" />
          <mpa:quantity-unit-lx v="03" lexicon="quantity-unit-lx" />
          <mpa:quantity-unit-alt-lx v="EQ" lexicon="quantity-unit-alt-lx" />
          <mpa:substance-lx v="IDE4POC9U9DK1VERT1" />
        </npl:ingredient>
        <npl:ingredient id="ID1GVKQ2AA8KTWISRV" related-to-id="ID1GVKQ2AA8KTSLSRV" presentation-substance-name="Y">
          <mpa:ingredient-role-lx v="ARES" lexicon="ingredient-role-lx" />
          <mpa:quantity v="13.5" />
          <mpa:quantity-unit-lx v="03" lexicon="quantity-unit-lx" />
          <mpa:quantity-unit-alt-lx v="EQ" lexicon="quantity-unit-alt-lx" />
          <mpa:substance-lx v="IDE4POCAU9EBBVERT1" />
        </npl:ingredient>
        <npl:ingredient id="ID1SPXTTXRR1EBDSRV">
          <mpa:ingredient-role-lx v="MISC" lexicon="ingredient-role-lx" />
          <mpa:substance-lx v="IDE4POC3U989HVERT1" />
        </npl:ingredient>
        <npl:ingredient id="ID1SPXTUNRR1YLFSRV">
          <mpa:ingredient-role-lx v="MISC" lexicon="ingredient-role-lx" />
          <mpa:substance-lx v="IDE4POI8UC9O7VERT1" />
        </npl:ingredient>
      </npl:composition>
      <mpa:comp-ref-quantity-lx v="FGE" lexicon="comp-ref-quantity-lx" />
    </npl:pharmaceutical-product>
  </npl:pharmaceutical-products>
  <mpa:dosdisp-life v="6" />
  <npl:packages>
    <npl:package>
      <mpa:nplpackid>20130130100319</mpa:nplpackid>
      <mpa:pack-text>
        <mpa:v>Blister, 10 tabletter</mpa:v>
      </mpa:pack-text>
      <mpa:pack-withdrawaldate>2020-11-05</mpa:pack-withdrawaldate>
      <npl:prescription>
        <mpa:otc v="N" lexicon="yesno-lx" />
      </npl:prescription>
      <mpa:safety-features v="Y" lexicon="yesno-lx" />
      <npl:storage>
        <mpa:pack-condition-lx v="1" lexicon="pack-condition-lx" id="ID1SPY8FERUXXANSRV" pharmaceutical-product-id="ID1GVKQ29A8KTOPSRV">
          <mpa:shelf-life v="3">
            <mpa:shelf-life-unit-lx v="5" lexicon="shelf-life-unit-lx" />
            <mpa:storage-temp-lx v="3" lexicon="storage-temp-lx" />
          </mpa:shelf-life>
        </mpa:pack-condition-lx>
      </npl:storage>
    </npl:package>
    <npl:package>
      <mpa:nplpackid>20130130100333</mpa:nplpackid>
      <mpa:pack-text>
        <mpa:v>Blister, 100 tabletter</mpa:v>
      </mpa:pack-text>
      <mpa:pack-withdrawaldate>2020-11-05</mpa:pack-withdrawaldate>
      <npl:prescription>
        <mpa:otc v="N" lexicon="yesno-lx" />
      </npl:prescription>
      <mpa:safety-features v="Y" lexicon="yesno-lx" />
      <npl:storage>
        <mpa:pack-condition-lx v="1" lexicon="pack-condition-lx" id="ID1SPY8K0RUZRW7SRV" pharmaceutical-product-id="ID1GVKQ29A8KTOPSRV">
          <mpa:shelf-life v="3">
            <mpa:shelf-life-unit-lx v="5" lexicon="shelf-life-unit-lx" />
            <mpa:storage-temp-lx v="3" lexicon="storage-temp-lx" />
          </mpa:shelf-life>
        </mpa:pack-condition-lx>
      </npl:storage>
    </npl:package>
    <npl:package>
      <mpa:nplpackid>20130130100234</mpa:nplpackid>
      <mpa:pack-text>
        <mpa:v>Blister, 100 tabletter (10 x 10), sjukhusförpackning</mpa:v>
      </mpa:pack-text>
      <mpa:pack-withdrawaldate>2020-11-05</mpa:pack-withdrawaldate>
      <npl:prescription>
        <mpa:otc v="N" lexicon="yesno-lx" />
      </npl:prescription>
      <mpa:safety-features v="Y" lexicon="yesno-lx" />
      <npl:storage>
        <mpa:pack-condition-lx v="1" lexicon="pack-condition-lx" id="ID1SPY8K6RUZWIVSRV" pharmaceutical-product-id="ID1GVKQ29A8KTOPSRV">
          <mpa:shelf-life v="3">
            <mpa:shelf-life-unit-lx v="5" lexicon="shelf-life-unit-lx" />
            <mpa:storage-temp-lx v="3" lexicon="storage-temp-lx" />
          </mpa:shelf-life>
        </mpa:pack-condition-lx>
      </npl:storage>
    </npl:package>
    <npl:package>
      <mpa:nplpackid>20130130100302</mpa:nplpackid>
      <mpa:pack-text>
        <mpa:v>Blister, 14 tabletter</mpa:v>
      </mpa:pack-text>
      <mpa:pack-withdrawaldate>2020-11-05</mpa:pack-withdrawaldate>
      <npl:prescription>
        <mpa:otc v="N" lexicon="yesno-lx" />
      </npl:prescription>
      <mpa:safety-features v="Y" lexicon="yesno-lx" />
      <npl:storage>
        <mpa:pack-condition-lx v="1" lexicon="pack-condition-lx" id="ID1SPY8HERUYMGGSRV" pharmaceutical-product-id="ID1GVKQ29A8KTOPSRV">
          <mpa:shelf-life v="3">
            <mpa:shelf-life-unit-lx v="5" lexicon="shelf-life-unit-lx" />
            <mpa:storage-temp-lx v="3" lexicon="storage-temp-lx" />
          </mpa:shelf-life>
        </mpa:pack-condition-lx>
      </npl:storage>
    </npl:package>
    <npl:package>
      <mpa:nplpackid>20130130100272</mpa:nplpackid>
      <mpa:pack-text>
        <mpa:v>Blister, 20 tabletter</mpa:v>
      </mpa:pack-text>
      <mpa:pack-withdrawaldate>2020-11-05</mpa:pack-withdrawaldate>
      <npl:prescription>
        <mpa:otc v="N" lexicon="yesno-lx" />
      </npl:prescription>
      <mpa:safety-features v="Y" lexicon="yesno-lx" />
      <npl:storage>
        <mpa:pack-condition-lx v="1" lexicon="pack-condition-lx" id="ID1SPY8HLRUYRMNSRV" pharmaceutical-product-id="ID1GVKQ29A8KTOPSRV">
          <mpa:shelf-life v="3">
            <mpa:shelf-life-unit-lx v="5" lexicon="shelf-life-unit-lx" />
            <mpa:storage-temp-lx v="3" lexicon="storage-temp-lx" />
          </mpa:shelf-life>
        </mpa:pack-condition-lx>
      </npl:storage>
    </npl:package>
    <npl:package>
      <mpa:nplpackid>20130130100265</mpa:nplpackid>
      <mpa:pack-text>
        <mpa:v>Blister, 28 tabletter</mpa:v>
      </mpa:pack-text>
      <mpa:pack-withdrawaldate>2020-11-05</mpa:pack-withdrawaldate>
      <npl:prescription>
        <mpa:otc v="N" lexicon="yesno-lx" />
      </npl:prescription>
      <mpa:safety-features v="Y" lexicon="yesno-lx" />
      <npl:storage>
        <mpa:pack-condition-lx v="1" lexicon="pack-condition-lx" id="ID1SPY8HRRUYW2DSRV" pharmaceutical-product-id="ID1GVKQ29A8KTOPSRV">
          <mpa:shelf-life v="3">
            <mpa:shelf-life-unit-lx v="5" lexicon="shelf-life-unit-lx" />
            <mpa:storage-temp-lx v="3" lexicon="storage-temp-lx" />
          </mpa:shelf-life>
        </mpa:pack-condition-lx>
      </npl:storage>
    </npl:package>
    <npl:package>
      <mpa:nplpackid>20130130100241</mpa:nplpackid>
      <mpa:pack-text>
        <mpa:v>Blister, 30 tabletter</mpa:v>
      </mpa:pack-text>
      <mpa:pack-withdrawaldate>2020-11-05</mpa:pack-withdrawaldate>
      <npl:prescription>
        <mpa:otc v="N" lexicon="yesno-lx" />
      </npl:prescription>
      <mpa:safety-features v="Y" lexicon="yesno-lx" />
      <npl:storage>
        <mpa:pack-condition-lx v="1" lexicon="pack-condition-lx" id="ID1SPY8HXRUZ0O6SRV" pharmaceutical-product-id="ID1GVKQ29A8KTOPSRV">
          <mpa:shelf-life v="3">
            <mpa:shelf-life-unit-lx v="5" lexicon="shelf-life-unit-lx" />
            <mpa:storage-temp-lx v="3" lexicon="storage-temp-lx" />
          </mpa:shelf-life>
        </mpa:pack-condition-lx>
      </npl:storage>
    </npl:package>
    <npl:package>
      <mpa:nplpackid>20130130100326</mpa:nplpackid>
      <mpa:pack-text>
        <mpa:v>Blister, 50 tabletter</mpa:v>
      </mpa:pack-text>
      <mpa:pack-withdrawaldate>2020-11-05</mpa:pack-withdrawaldate>
      <npl:prescription>
        <mpa:otc v="N" lexicon="yesno-lx" />
      </npl:prescription>
      <mpa:safety-features v="Y" lexicon="yesno-lx" />
      <npl:storage>
        <mpa:pack-condition-lx v="1" lexicon="pack-condition-lx" id="ID1SPY8I5RUZ6UESRV" pharmaceutical-product-id="ID1GVKQ29A8KTOPSRV">
          <mpa:shelf-life v="3">
            <mpa:shelf-life-unit-lx v="5" lexicon="shelf-life-unit-lx" />
            <mpa:storage-temp-lx v="3" lexicon="storage-temp-lx" />
          </mpa:shelf-life>
        </mpa:pack-condition-lx>
      </npl:storage>
    </npl:package>
    <npl:package>
      <mpa:nplpackid>20130130100258</mpa:nplpackid>
      <mpa:pack-text>
        <mpa:v>Blister, 56 tabletter</mpa:v>
      </mpa:pack-text>
      <mpa:pack-withdrawaldate>2020-11-05</mpa:pack-withdrawaldate>
      <npl:prescription>
        <mpa:otc v="N" lexicon="yesno-lx" />
      </npl:prescription>
      <mpa:safety-features v="Y" lexicon="yesno-lx" />
      <npl:storage>
        <mpa:pack-condition-lx v="1" lexicon="pack-condition-lx" id="ID1SPY8ICRUZC7JSRV" pharmaceutical-product-id="ID1GVKQ29A8KTOPSRV">
          <mpa:shelf-life v="3">
            <mpa:shelf-life-unit-lx v="5" lexicon="shelf-life-unit-lx" />
            <mpa:storage-temp-lx v="3" lexicon="storage-temp-lx" />
          </mpa:shelf-life>
        </mpa:pack-condition-lx>
      </npl:storage>
    </npl:package>
    <npl:package>
      <mpa:nplpackid>20130130100296</mpa:nplpackid>
      <mpa:pack-text>
        <mpa:v>Blister, 60 tabletter</mpa:v>
      </mpa:pack-text>
      <mpa:pack-withdrawaldate>2020-11-05</mpa:pack-withdrawaldate>
      <npl:prescription>
        <mpa:otc v="N" lexicon="yesno-lx" />
      </npl:prescription>
      <mpa:safety-features v="Y" lexicon="yesno-lx" />
      <npl:storage>
        <mpa:pack-condition-lx v="1" lexicon="pack-condition-lx" id="ID1SPY8IHRUZGP0SRV" pharmaceutical-product-id="ID1GVKQ29A8KTOPSRV">
          <mpa:shelf-life v="3">
            <mpa:shelf-life-unit-lx v="5" lexicon="shelf-life-unit-lx" />
            <mpa:storage-temp-lx v="3" lexicon="storage-temp-lx" />
          </mpa:shelf-life>
        </mpa:pack-condition-lx>
      </npl:storage>
    </npl:package>
    <npl:package>
      <mpa:nplpackid>20130130100289</mpa:nplpackid>
      <mpa:pack-text>
        <mpa:v>Blister, 98 tabletter</mpa:v>
      </mpa:pack-text>
      <mpa:pack-withdrawaldate>2020-11-05</mpa:pack-withdrawaldate>
      <npl:prescription>
        <mpa:otc v="N" lexicon="yesno-lx" />
      </npl:prescription>
      <mpa:safety-features v="Y" lexicon="yesno-lx" />
      <npl:storage>
        <mpa:pack-condition-lx v="1" lexicon="pack-condition-lx" id="ID1SPY8JSRUZLNTSRV" pharmaceutical-product-id="ID1GVKQ29A8KTOPSRV">
          <mpa:shelf-life v="3">
            <mpa:shelf-life-unit-lx v="5" lexicon="shelf-life-unit-lx" />
            <mpa:storage-temp-lx v="3" lexicon="storage-temp-lx" />
          </mpa:shelf-life>
        </mpa:pack-condition-lx>
      </npl:storage>
    </npl:package>
  </npl:packages>
</npl:medprod>
