<?xml version="1.0"?>
<npl:medprod xmlns:xsi="http://www.w3.org/2001/XMLSchema-instance" xmlns:mpa="urn:schemas-npl:mpa:12" xsi:schemaLocation="urn:schemas-npl:instance:12 ../schemas/npl-schema_12.0.xsd" xmlns:npl="urn:schemas-npl:instance:12">
  <mpa:nplid>20160730000047</mpa:nplid>
  <npl:approvalnumber>
    <mpa:semano>551630</mpa:semano>
    <mpa:nat-ma-no>55163</mpa:nat-ma-no>
  </npl:approvalnumber>
  <npl:names>
    <mpa:medprodname v="Lyribastad" />
    <mpa:medprodnamelegal v="Lyribastad" />
  </npl:names>
  <mpa:strength-text>
    <mpa:v>100 mg</mpa:v>
  </mpa:strength-text>
  <mpa:pharmaceutical-form-lx v="CAPHAR" lexicon="pharmaceutical-form-lx" />
  <npl:route-of-administrations>
    <mpa:route-of-administration-lx v="ORAL" lexicon="route-of-administration-lx" />
  </npl:route-of-administrations>
  <npl:organizations>
    <mpa:organization>
      <mpa:organization-lx v="ID147OJZC3HYGBPSRV" />
      <mpa:organization-role-lx v="AGENT" lexicon="organization-role-lx" />
    </mpa:organization>
    <mpa:organization>
      <mpa:organization-lx v="IDFRNXSS15I57H0CSR" />
      <mpa:organization-role-lx v="MAH" lexicon="organization-role-lx" />
    </mpa:organization>
  </npl:organizations>
  <mpa:approvaldate>2017-12-15</mpa:approvaldate>
  <mpa:productclass-lx v="MEP" lexicon="productclass-lx" />
  <mpa:prescription-lx v="1" lexicon="prescription-lx" />
  <npl:classifications>
    <mpa:atc-code-lx v="N02BF02" />
    <mpa:controlled-medicinal-product-lx v="Y" lexicon="yesno-lx" />
    <mpa:repeat-prescription-lx v="004" lexicon="repeat-prescription-lx" />
    <mpa:narcotic-class-lx v="5" lexicon="narcotic-classification-lx" />
  </npl:classifications>
  <mpa:authorisation-procedure-lx v="4" lexicon="authorisation-procedure-lx" />
  <npl:flags>
    <mpa:salesstopped v="N" lexicon="yesno-lx" />
    <mpa:biological-medprod-pharmaceutical-legislation v="N" lexicon="yesno-lx" />
    <mpa:antimicrobial v="N" lexicon="yesno-lx" />
    <mpa:reserved-hum v="N" lexicon="yesno-lx" />
  </npl:flags>
  <npl:pharmaceutical-products>
    <npl:pharmaceutical-product id="IDXRL66G1B56WDSRV0">
      <npl:composition>
        <npl:ingredient id="IDXRL66G1B573ASRV0" presentation-substance-name="Y" substance-for-reference-strength="Y">
          <mpa:ingredient-role-lx v="ACTI" lexicon="ingredient-role-lx" />
          <mpa:quantity v="100" />
          <mpa:quantity-unit-lx v="03" lexicon="quantity-unit-lx" />
          <mpa:quantity-unit-alt-lx v="EQ" lexicon="quantity-unit-alt-lx" />
          <mpa:substance-lx v="IDSCYTWF8S8JD4MSRV" />
        </npl:ingredient>
        <npl:ingredient id="IDXRL66G1B578HSRV0">
          <mpa:ingredient-role-lx v="MISC" lexicon="ingredient-role-lx" />
          <mpa:substance-lx v="IDE4POI8UC9O7VERT1" />
        </npl:ingredient>
      </npl:composition>
      <mpa:comp-ref-quantity-lx v="FGE" lexicon="comp-ref-quantity-lx" />
    </npl:pharmaceutical-product>
  </npl:pharmaceutical-products>
  <npl:packages>
    <npl:package>
      <mpa:nplpackid>20171208100527</mpa:nplpackid>
      <mpa:pack-text>
        <mpa:v>Blister, 100 kapslar</mpa:v>
      </mpa:pack-text>
      <npl:prescription>
        <mpa:otc v="N" lexicon="yesno-lx" />
      </npl:prescription>
      <mpa:safety-features v="Y" lexicon="yesno-lx" />
      <npl:storage>
        <mpa:pack-condition-lx v="1" lexicon="pack-condition-lx" id="IDXRLETU1DQ07YSRV0" pharmaceutical-product-id="IDXRL66G1B56WDSRV0">
          <mpa:shelf-life v="3">
            <mpa:shelf-life-unit-lx v="5" lexicon="shelf-life-unit-lx" />
            <mpa:storage-temp-lx v="1" lexicon="storage-temp-lx" />
          </mpa:shelf-life>
        </mpa:pack-condition-lx>
      </npl:storage>
    </npl:package>
    <npl:package>
      <mpa:nplpackid>20200703101958</mpa:nplpackid>
      <mpa:pack-text>
        <mpa:v>Blister, 100 x 1 kapslar (endos)</mpa:v>
      </mpa:pack-text>
      <npl:prescription>
        <mpa:otc v="N" lexicon="yesno-lx" />
      </npl:prescription>
      <mpa:safety-features v="Y" lexicon="yesno-lx" />
      <npl:storage>
        <mpa:pack-condition-lx v="1" lexicon="pack-condition-lx" id="IDOCDLZ3DSMZFMSRV0" pharmaceutical-product-id="IDXRL66G1B56WDSRV0">
          <mpa:shelf-life v="3">
            <mpa:shelf-life-unit-lx v="5" lexicon="shelf-life-unit-lx" />
            <mpa:storage-temp-lx v="1" lexicon="storage-temp-lx" />
          </mpa:shelf-life>
        </mpa:pack-condition-lx>
      </npl:storage>
    </npl:package>
    <npl:package>
      <mpa:nplpackid>20171208100497</mpa:nplpackid>
      <mpa:pack-text>
        <mpa:v>Blister, 14 kapslar</mpa:v>
      </mpa:pack-text>
      <npl:prescription>
        <mpa:otc v="N" lexicon="yesno-lx" />
      </npl:prescription>
      <mpa:safety-features v="Y" lexicon="yesno-lx" />
      <npl:storage>
        <mpa:pack-condition-lx v="1" lexicon="pack-condition-lx" id="IDXRLESM1DP1MKSRV0" pharmaceutical-product-id="IDXRL66G1B56WDSRV0">
          <mpa:shelf-life v="3">
            <mpa:shelf-life-unit-lx v="5" lexicon="shelf-life-unit-lx" />
            <mpa:storage-temp-lx v="1" lexicon="storage-temp-lx" />
          </mpa:shelf-life>
        </mpa:pack-condition-lx>
      </npl:storage>
    </npl:package>
    <npl:package>
      <mpa:nplpackid>20200703102016</mpa:nplpackid>
      <mpa:pack-text>
        <mpa:v>Blister, 14 x 1 kapslar (endos)</mpa:v>
      </mpa:pack-text>
      <npl:prescription>
        <mpa:otc v="N" lexicon="yesno-lx" />
      </npl:prescription>
      <mpa:safety-features v="Y" lexicon="yesno-lx" />
      <npl:storage>
        <mpa:pack-condition-lx v="1" lexicon="pack-condition-lx" id="IDOCDLZ7DSN2KWSRV0" pharmaceutical-product-id="IDXRL66G1B56WDSRV0">
          <mpa:shelf-life v="3">
            <mpa:shelf-life-unit-lx v="5" lexicon="shelf-life-unit-lx" />
            <mpa:storage-temp-lx v="1" lexicon="storage-temp-lx" />
          </mpa:shelf-life>
        </mpa:pack-condition-lx>
      </npl:storage>
    </npl:package>
    <npl:package>
      <mpa:nplpackid>20171208100510</mpa:nplpackid>
      <mpa:pack-text>
        <mpa:v>Blister, 200 kapslar</mpa:v>
      </mpa:pack-text>
      <npl:prescription>
        <mpa:otc v="N" lexicon="yesno-lx" />
      </npl:prescription>
      <mpa:safety-features v="Y" lexicon="yesno-lx" />
      <npl:storage>
        <mpa:pack-condition-lx v="1" lexicon="pack-condition-lx" id="IDXRLETU1DPZLFSRV0" pharmaceutical-product-id="IDXRL66G1B56WDSRV0">
          <mpa:shelf-life v="3">
            <mpa:shelf-life-unit-lx v="5" lexicon="shelf-life-unit-lx" />
            <mpa:storage-temp-lx v="1" lexicon="storage-temp-lx" />
          </mpa:shelf-life>
        </mpa:pack-condition-lx>
      </npl:storage>
    </npl:package>
    <npl:package>
      <mpa:nplpackid>20200703101934</mpa:nplpackid>
      <mpa:pack-text>
        <mpa:v>Blister, 200 x 1 kapslar (endos)</mpa:v>
      </mpa:pack-text>
      <npl:prescription>
        <mpa:otc v="N" lexicon="yesno-lx" />
      </npl:prescription>
      <mpa:safety-features v="Y" lexicon="yesno-lx" />
      <npl:storage>
        <mpa:pack-condition-lx v="1" lexicon="pack-condition-lx" id="IDOCDLWYDSM6WPSRV0" pharmaceutical-product-id="IDXRL66G1B56WDSRV0">
          <mpa:shelf-life v="3">
            <mpa:shelf-life-unit-lx v="5" lexicon="shelf-life-unit-lx" />
            <mpa:storage-temp-lx v="1" lexicon="storage-temp-lx" />
          </mpa:shelf-life>
        </mpa:pack-condition-lx>
      </npl:storage>
    </npl:package>
    <npl:package>
      <mpa:nplpackid>20171208100572</mpa:nplpackid>
      <mpa:pack-text>
        <mpa:v>Blister, 21 kapslar</mpa:v>
      </mpa:pack-text>
      <npl:prescription>
        <mpa:otc v="N" lexicon="yesno-lx" />
      </npl:prescription>
      <mpa:safety-features v="Y" lexicon="yesno-lx" />
      <npl:storage>
        <mpa:pack-condition-lx v="1" lexicon="pack-condition-lx" id="IDXRLETZ1DQ3GYSRV0" pharmaceutical-product-id="IDXRL66G1B56WDSRV0">
          <mpa:shelf-life v="3">
            <mpa:shelf-life-unit-lx v="5" lexicon="shelf-life-unit-lx" />
            <mpa:storage-temp-lx v="1" lexicon="storage-temp-lx" />
          </mpa:shelf-life>
        </mpa:pack-condition-lx>
      </npl:storage>
    </npl:package>
    <npl:package>
      <mpa:nplpackid>20200703102009</mpa:nplpackid>
      <mpa:pack-text>
        <mpa:v>Blister, 21 x 1 kapslar (endos)</mpa:v>
      </mpa:pack-text>
      <npl:prescription>
        <mpa:otc v="N" lexicon="yesno-lx" />
      </npl:prescription>
      <mpa:safety-features v="Y" lexicon="yesno-lx" />
      <npl:storage>
        <mpa:pack-condition-lx v="1" lexicon="pack-condition-lx" id="IDOCDLZ6DSN234SRV0" pharmaceutical-product-id="IDXRL66G1B56WDSRV0">
          <mpa:shelf-life v="3">
            <mpa:shelf-life-unit-lx v="5" lexicon="shelf-life-unit-lx" />
            <mpa:storage-temp-lx v="1" lexicon="storage-temp-lx" />
          </mpa:shelf-life>
        </mpa:pack-condition-lx>
      </npl:storage>
    </npl:package>
    <npl:package>
      <mpa:nplpackid>20171208100503</mpa:nplpackid>
      <mpa:pack-text>
        <mpa:v>Blister, 210 kapslar</mpa:v>
      </mpa:pack-text>
      <npl:prescription>
        <mpa:otc v="N" lexicon="yesno-lx" />
      </npl:prescription>
      <mpa:safety-features v="Y" lexicon="yesno-lx" />
      <npl:storage>
        <mpa:pack-condition-lx v="1" lexicon="pack-condition-lx" id="IDXRLETT1DPZ2DSRV0" pharmaceutical-product-id="IDXRL66G1B56WDSRV0">
          <mpa:shelf-life v="3">
            <mpa:shelf-life-unit-lx v="5" lexicon="shelf-life-unit-lx" />
            <mpa:storage-temp-lx v="1" lexicon="storage-temp-lx" />
          </mpa:shelf-life>
        </mpa:pack-condition-lx>
      </npl:storage>
    </npl:package>
    <npl:package>
      <mpa:nplpackid>20200703101941</mpa:nplpackid>
      <mpa:pack-text>
        <mpa:v>Blister, 210 x 1 kapslar (endos)</mpa:v>
      </mpa:pack-text>
      <npl:prescription>
        <mpa:otc v="N" lexicon="yesno-lx" />
      </npl:prescription>
      <mpa:safety-features v="Y" lexicon="yesno-lx" />
      <npl:storage>
        <mpa:pack-condition-lx v="1" lexicon="pack-condition-lx" id="IDOCDLZ2DSMYWJSRV0" pharmaceutical-product-id="IDXRL66G1B56WDSRV0">
          <mpa:shelf-life v="3">
            <mpa:shelf-life-unit-lx v="5" lexicon="shelf-life-unit-lx" />
            <mpa:storage-temp-lx v="1" lexicon="storage-temp-lx" />
          </mpa:shelf-life>
        </mpa:pack-condition-lx>
      </npl:storage>
    </npl:package>
    <npl:package>
      <mpa:nplpackid>20171208100565</mpa:nplpackid>
      <mpa:pack-text>
        <mpa:v>Blister, 30 kapslar</mpa:v>
      </mpa:pack-text>
      <npl:prescription>
        <mpa:otc v="N" lexicon="yesno-lx" />
      </npl:prescription>
      <mpa:safety-features v="Y" lexicon="yesno-lx" />
      <npl:storage>
        <mpa:pack-condition-lx v="1" lexicon="pack-condition-lx" id="IDXRLETY1DQ2WLSRV0" pharmaceutical-product-id="IDXRL66G1B56WDSRV0">
          <mpa:shelf-life v="3">
            <mpa:shelf-life-unit-lx v="5" lexicon="shelf-life-unit-lx" />
            <mpa:storage-temp-lx v="1" lexicon="storage-temp-lx" />
          </mpa:shelf-life>
        </mpa:pack-condition-lx>
      </npl:storage>
    </npl:package>
    <npl:package>
      <mpa:nplpackid>20200703101996</mpa:nplpackid>
      <mpa:pack-text>
        <mpa:v>Blister, 30 x 1 kapslar (endos)</mpa:v>
      </mpa:pack-text>
      <npl:prescription>
        <mpa:otc v="N" lexicon="yesno-lx" />
      </npl:prescription>
      <mpa:safety-features v="Y" lexicon="yesno-lx" />
      <npl:storage>
        <mpa:pack-condition-lx v="1" lexicon="pack-condition-lx" id="IDOCDLZ6DSN1KGSRV0" pharmaceutical-product-id="IDXRL66G1B56WDSRV0">
          <mpa:shelf-life v="3">
            <mpa:shelf-life-unit-lx v="5" lexicon="shelf-life-unit-lx" />
            <mpa:storage-temp-lx v="1" lexicon="storage-temp-lx" />
          </mpa:shelf-life>
        </mpa:pack-condition-lx>
      </npl:storage>
    </npl:package>
    <npl:package>
      <mpa:nplpackid>20171208100558</mpa:nplpackid>
      <mpa:pack-text>
        <mpa:v>Blister, 56 kapslar</mpa:v>
      </mpa:pack-text>
      <npl:prescription>
        <mpa:otc v="N" lexicon="yesno-lx" />
      </npl:prescription>
      <mpa:safety-features v="Y" lexicon="yesno-lx" />
      <npl:storage>
        <mpa:pack-condition-lx v="1" lexicon="pack-condition-lx" id="IDXRLETX1DQ24VSRV0" pharmaceutical-product-id="IDXRL66G1B56WDSRV0">
          <mpa:shelf-life v="3">
            <mpa:shelf-life-unit-lx v="5" lexicon="shelf-life-unit-lx" />
            <mpa:storage-temp-lx v="1" lexicon="storage-temp-lx" />
          </mpa:shelf-life>
        </mpa:pack-condition-lx>
      </npl:storage>
    </npl:package>
    <npl:package>
      <mpa:nplpackid>20200703101989</mpa:nplpackid>
      <mpa:pack-text>
        <mpa:v>Blister, 56 x 1 kapslar (endos)</mpa:v>
      </mpa:pack-text>
      <npl:prescription>
        <mpa:otc v="N" lexicon="yesno-lx" />
      </npl:prescription>
      <mpa:safety-features v="Y" lexicon="yesno-lx" />
      <npl:storage>
        <mpa:pack-condition-lx v="1" lexicon="pack-condition-lx" id="IDOCDLZ5DSN128SRV0" pharmaceutical-product-id="IDXRL66G1B56WDSRV0">
          <mpa:shelf-life v="3">
            <mpa:shelf-life-unit-lx v="5" lexicon="shelf-life-unit-lx" />
            <mpa:storage-temp-lx v="1" lexicon="storage-temp-lx" />
          </mpa:shelf-life>
        </mpa:pack-condition-lx>
      </npl:storage>
    </npl:package>
    <npl:package>
      <mpa:nplpackid>20171208100541</mpa:nplpackid>
      <mpa:pack-text>
        <mpa:v>Blister, 60 kapslar</mpa:v>
      </mpa:pack-text>
      <npl:prescription>
        <mpa:otc v="N" lexicon="yesno-lx" />
      </npl:prescription>
      <mpa:safety-features v="Y" lexicon="yesno-lx" />
      <npl:storage>
        <mpa:pack-condition-lx v="1" lexicon="pack-condition-lx" id="IDXRLETW1DQ1GLSRV0" pharmaceutical-product-id="IDXRL66G1B56WDSRV0">
          <mpa:shelf-life v="3">
            <mpa:shelf-life-unit-lx v="5" lexicon="shelf-life-unit-lx" />
            <mpa:storage-temp-lx v="1" lexicon="storage-temp-lx" />
          </mpa:shelf-life>
        </mpa:pack-condition-lx>
      </npl:storage>
    </npl:package>
    <npl:package>
      <mpa:nplpackid>20200703101972</mpa:nplpackid>
      <mpa:pack-text>
        <mpa:v>Blister, 60 x 1 kapslar (endos)</mpa:v>
      </mpa:pack-text>
      <npl:prescription>
        <mpa:otc v="N" lexicon="yesno-lx" />
      </npl:prescription>
      <mpa:safety-features v="Y" lexicon="yesno-lx" />
      <npl:storage>
        <mpa:pack-condition-lx v="1" lexicon="pack-condition-lx" id="IDOCDLZ4DSN0I9SRV0" pharmaceutical-product-id="IDXRL66G1B56WDSRV0">
          <mpa:shelf-life v="3">
            <mpa:shelf-life-unit-lx v="5" lexicon="shelf-life-unit-lx" />
            <mpa:storage-temp-lx v="1" lexicon="storage-temp-lx" />
          </mpa:shelf-life>
        </mpa:pack-condition-lx>
      </npl:storage>
    </npl:package>
    <npl:package>
      <mpa:nplpackid>20171208100534</mpa:nplpackid>
      <mpa:pack-text>
        <mpa:v>Blister, 84 kapslar</mpa:v>
      </mpa:pack-text>
      <npl:prescription>
        <mpa:otc v="N" lexicon="yesno-lx" />
      </npl:prescription>
      <mpa:safety-features v="Y" lexicon="yesno-lx" />
      <npl:storage>
        <mpa:pack-condition-lx v="1" lexicon="pack-condition-lx" id="IDXRLETV1DQ0U2SRV0" pharmaceutical-product-id="IDXRL66G1B56WDSRV0">
          <mpa:shelf-life v="3">
            <mpa:shelf-life-unit-lx v="5" lexicon="shelf-life-unit-lx" />
            <mpa:storage-temp-lx v="1" lexicon="storage-temp-lx" />
          </mpa:shelf-life>
        </mpa:pack-condition-lx>
      </npl:storage>
    </npl:package>
    <npl:package>
      <mpa:nplpackid>20200703101965</mpa:nplpackid>
      <mpa:pack-text>
        <mpa:v>Blister, 84 x 1 kapslar (endos)</mpa:v>
      </mpa:pack-text>
      <npl:prescription>
        <mpa:otc v="N" lexicon="yesno-lx" />
      </npl:prescription>
      <mpa:safety-features v="Y" lexicon="yesno-lx" />
      <npl:storage>
        <mpa:pack-condition-lx v="1" lexicon="pack-condition-lx" id="IDOCDLZ3DSMZZ5SRV0" pharmaceutical-product-id="IDXRL66G1B56WDSRV0">
          <mpa:shelf-life v="3">
            <mpa:shelf-life-unit-lx v="5" lexicon="shelf-life-unit-lx" />
            <mpa:storage-temp-lx v="1" lexicon="storage-temp-lx" />
          </mpa:shelf-life>
        </mpa:pack-condition-lx>
      </npl:storage>
    </npl:package>
  </npl:packages>
</npl:medprod>
